murainbot/__init__.py
murainbot/_defaults.py
murainbot/cli.py
murainbot/common.py
murainbot/main.py
murainbot/paths.py
murainbot/core/ConfigManager.py
murainbot/core/EventManager.py
murainbot/core/ListenerServer.py
murainbot/core/OnebotAPI.py
murainbot/core/PluginManager.py
murainbot/core/ThreadPool.py
murainbot/templates/plugins/Helper.py
murainbot/templates/plugins/LagrangeExtension/Actions.py
murainbot/templates/plugins/LagrangeExtension/Events.py
murainbot/templates/plugins/LagrangeExtension/Segments.py
murainbot/templates/plugins/LagrangeExtension/__init__.py
murainbot/utils/Actions.py
murainbot/utils/AutoRestartOnebot.py
murainbot/utils/EventClassifier.py
murainbot/utils/EventHandlers.py
murainbot/utils/Logger.py
murainbot/utils/PluginConfig.py
murainbot/utils/QQDataCacher.py
murainbot/utils/QQDataCacher.pyi
murainbot/utils/QQRichText.py
murainbot/utils/SessionManager.py
murainbot/utils/StateManager.py
murainbot/utils/TimerManager.py
murainbot/utils/__init__.py
murainbot/utils/CommandManager/__init__.py
murainbot/utils/CommandManager/args.py
murainbot/utils/CommandManager/matcher.py
murainbot-0.4.1.dist-info/licenses/LICENSE
murainbot-0.4.1.dist-info/METADATA
murainbot-0.4.1.dist-info/WHEEL
murainbot-0.4.1.dist-info/entry_points.txt
murainbot-0.4.1.dist-info/top_level.txt
murainbot-0.4.1.dist-info/RECORD
