Metadata-Version: 2.4
Name: murainbot
Version: 0.4.1
Summary: 一个基于python适配onebot11协议的轻量级Onebot框架/QQ机器人框架/QQBot框架
Author-email: Xiaosu <xiaosu@xiaosu.icu>
Project-URL: Homepage, https://github.com/MuRainBot/MuRainBot2
Project-URL: Repository, https://github.com/MuRainBot/MuRainBot2
Project-URL: Documentation, https://mrb2.xiaosu.icu/
Project-URL: Bug Tracker, https://github.com/MuRainBot/MuRainBot2/issues
Classifier: Development Status :: 3 - Alpha
Classifier: Framework :: Robot Framework
Classifier: Framework :: Robot Framework :: Library
Classifier: Operating System :: OS Independent
Classifier: Programming Language :: Python :: 3
Classifier: Programming Language :: Python :: 3.12
Requires-Python: >=3.12
License-File: LICENSE
Requires-Dist: requests>=2.31.0
Requires-Dist: PyYAML>=6.0
Requires-Dist: Flask>=3.0.0
Requires-Dist: Werkzeug>=3.0.0
Requires-Dist: typer>=0.9.0
Requires-Dist: rich>=13.0.0
Dynamic: license-file
